cd_fargate_express/__init__.py
cd_fargate_express/py.typed
cd_fargate_express/_jsii/__init__.py
cd_fargate_express/_jsii/cdk-fargate-express@0.4.305.jsii.tgz
cdk_fargate_express-0.4.305.dist-info/LICENSE
cdk_fargate_express-0.4.305.dist-info/METADATA
cdk_fargate_express-0.4.305.dist-info/WHEEL
cdk_fargate_express-0.4.305.dist-info/top_level.txt
cdk_fargate_express-0.4.305.dist-info/RECORD
